excelsync/__init__.py
excelsync/excel_sync.py
excelsync/schema.py
excelsync-0.1.0.dist-info/licenses/LICENSE
excelsync-0.1.0.dist-info/METADATA
excelsync-0.1.0.dist-info/WHEEL
excelsync-0.1.0.dist-info/top_level.txt
excelsync-0.1.0.dist-info/RECORD
