Metadata-Version: 2.4
Name: excelsync
Version: 0.1.0
Summary: Library for managing Excel sheets with predefined structures
Author-email: Joerg Seitter <joerg.seitter@hs-esslingen.de>
License-Expression: MIT
Classifier: Programming Language :: Python :: 3
Classifier: Operating System :: OS Independent
Requires-Python: >=3.8
License-File: LICENSE
Requires-Dist: openpyxl>=3.1.0
Requires-Dist: pyyaml>=6.0
Requires-Dist: jsonschema>=4.0.0
Provides-Extra: dev
Requires-Dist: pytest>=7.0.0; extra == "dev"
Requires-Dist: black>=23.0.0; extra == "dev"
Requires-Dist: flake8>=6.0.0; extra == "dev"
Requires-Dist: mypy>=1.0.0; extra == "dev"
Requires-Dist: types-openpyxl; extra == "dev"
Requires-Dist: types-PyYAML; extra == "dev"
Requires-Dist: types-jsonschema; extra == "dev"
Dynamic: license-file
